{"cameraMode":{"drawMode":0,"name":"Shaded","section":"Shading Mode"},"sceneLighting":true,"audioPlay":false,"sceneViewState":{"showFog":true,"showMaterialUpdate":false,"showSkybox":true,"showFlares":true,"showImageEffects":true,"showParticleSystems":true},"in2DMode":false,"pivot":{"x":-2.6375160217285158,"y":-0.18711566925048829,"z":-4.395276069641113},"rotation":{"x":-0.06036819517612457,"y":0.8762710094451904,"z":-0.11394605040550232,"w":-0.46424436569213869},"size":11.31950855255127,"orthographic":false}